Ultimate_Card_Deck/__init__.py
Ultimate_Card_Deck/deck_of_cards.py
Ultimate_Card_Deck/deck/10_of_clubs.png
Ultimate_Card_Deck/deck/10_of_diamonds.png
Ultimate_Card_Deck/deck/10_of_hearts.png
Ultimate_Card_Deck/deck/10_of_spades.png
Ultimate_Card_Deck/deck/2_of_clubs.png
Ultimate_Card_Deck/deck/2_of_diamonds.png
Ultimate_Card_Deck/deck/2_of_hearts.png
Ultimate_Card_Deck/deck/2_of_spades.png
Ultimate_Card_Deck/deck/3_of_clubs.png
Ultimate_Card_Deck/deck/3_of_diamonds.png
Ultimate_Card_Deck/deck/3_of_hearts.png
Ultimate_Card_Deck/deck/3_of_spades.png
Ultimate_Card_Deck/deck/4_of_clubs.png
Ultimate_Card_Deck/deck/4_of_diamonds.png
Ultimate_Card_Deck/deck/4_of_hearts.png
Ultimate_Card_Deck/deck/4_of_spades.png
Ultimate_Card_Deck/deck/5_of_clubs.png
Ultimate_Card_Deck/deck/5_of_diamonds.png
Ultimate_Card_Deck/deck/5_of_hearts.png
Ultimate_Card_Deck/deck/5_of_spades.png
Ultimate_Card_Deck/deck/6_of_clubs.png
Ultimate_Card_Deck/deck/6_of_diamonds.png
Ultimate_Card_Deck/deck/6_of_hearts.png
Ultimate_Card_Deck/deck/6_of_spades.png
Ultimate_Card_Deck/deck/7_of_clubs.png
Ultimate_Card_Deck/deck/7_of_diamonds.png
Ultimate_Card_Deck/deck/7_of_hearts.png
Ultimate_Card_Deck/deck/7_of_spades.png
Ultimate_Card_Deck/deck/8_of_clubs.png
Ultimate_Card_Deck/deck/8_of_diamonds.png
Ultimate_Card_Deck/deck/8_of_hearts.png
Ultimate_Card_Deck/deck/8_of_spades.png
Ultimate_Card_Deck/deck/9_of_clubs.png
Ultimate_Card_Deck/deck/9_of_diamonds.png
Ultimate_Card_Deck/deck/9_of_hearts.png
Ultimate_Card_Deck/deck/9_of_spades.png
Ultimate_Card_Deck/deck/ace_of_clubs.png
Ultimate_Card_Deck/deck/ace_of_diamonds.png
Ultimate_Card_Deck/deck/ace_of_hearts.png
Ultimate_Card_Deck/deck/ace_of_spades.png
Ultimate_Card_Deck/deck/ace_of_spades2.png
Ultimate_Card_Deck/deck/black_joker.png
Ultimate_Card_Deck/deck/card_back.PNG
Ultimate_Card_Deck/deck/jack_of_clubs.png
Ultimate_Card_Deck/deck/jack_of_clubs2.png
Ultimate_Card_Deck/deck/jack_of_diamonds.png
Ultimate_Card_Deck/deck/jack_of_diamonds2.png
Ultimate_Card_Deck-0.0.5.dist-info/LICENSE
Ultimate_Card_Deck-0.0.5.dist-info/METADATA
Ultimate_Card_Deck-0.0.5.dist-info/WHEEL
Ultimate_Card_Deck-0.0.5.dist-info/top_level.txt
Ultimate_Card_Deck-0.0.5.dist-info/RECORD
