Metadata-Version: 2.1
Name: Ultimate-Card-Deck
Version: 0.0.5
Summary: A deck of cards with basic functionality
Author-email: Patrick <pjo101689@gmail.com>
Project-URL: Homepage, https://github.com/pjo101010/Deck-of-Cards
Classifier: Programming Language :: Python :: 3
Classifier: License :: OSI Approved :: MIT License
Classifier: Operating System :: OS Independent
Requires-Python: >=3.7
License-File: LICENSE
